MANIFEST.in
README.md
setup.cfg
setup.py
src/Caliope_Odisea.egg-info/PKG-INFO
src/Caliope_Odisea.egg-info/SOURCES.txt
src/Caliope_Odisea.egg-info/dependency_links.txt
src/Caliope_Odisea.egg-info/requires.txt
src/Caliope_Odisea.egg-info/top_level.txt
src/odisea/CaliopeStorage.py
src/odisea/StorageUtils.py
src/odisea/__init__.py
src/test/TestCaliopeStorage.py