Metadata-Version: 1.0
Name: Caliope-Odisea
Version: 0.0.3
Summary: UNKNOWN
Home-page: https://proyectos.correlibre.org/caliope/caliope_storage_la_odisea
Author: Sebastian Ortiz Vásquez
Author-email: neoecos@gmail.com
License: GNU AFFERO GENERAL PUBLIC LICENSE
Platform: UNKNOWN
